{
  "species": "cobblemon:yandement",
  "order": 1,
  "variations": [
    {
      "aspects": [
        "fratzkian"
      ],
      "poser": "cobblemon:yandement_fratzki",
      "model": "cobblemon:yandement_fratzki.geo",
      "texture": "cobblemon:textures/pokemon/yandement/yandement_fratzki.png",
      "layers": [
	{
        "name": "signature-color",
        "texture": "cobblemon:textures/pokemon/yandement/yandement_fratzki_emissive.png",
        "emissive": "true"
        }
	]
    },
    {
      "aspects": [
        "fratzkian",
        "shiny"
      ],
      "texture": "cobblemon:textures/pokemon/yandement/yandement_fratzki_shiny.png",
      "layers": [
	{
        "name": "signature-color",
        "texture": "cobblemon:textures/pokemon/yandement/yandement_fratzki_shiny_emissive.png",
        "emissive": "true"
        }
	]
    }
  ]
}
